mmuxer-0.6.7.dist-info/METADATA
mmuxer-0.6.7.dist-info/WHEEL
mmuxer-0.6.7.dist-info/entry_points.txt
mmuxer-0.6.7.dist-info/licenses/LICENSE
mmuxer/MANIFEST.in
mmuxer/__init__.py
mmuxer/__main__.py
mmuxer/cli/__init__.py
mmuxer/cli/folder.py
mmuxer/cli/run.py
mmuxer/cli/sieve_export.py
mmuxer/config_state.py
mmuxer/mailbox.py
mmuxer/models/__init__.py
mmuxer/models/action.py
mmuxer/models/common.py
mmuxer/models/condition.py
mmuxer/models/enums.py
mmuxer/models/rule.py
mmuxer/models/script.py
mmuxer/models/settings.py
mmuxer/models/sieve.py
mmuxer/utils.py
mmuxer/workers.py
mmuxer-0.6.7.dist-info/RECORD
