Metadata-Version: 2.1
Name: mmuxer
Version: 0.6.7
Summary: Manage mail from your server.
Author-Email: Mathias Millet <mathias@mmill.eu>
License: AGPL-3.0
Classifier: Topic :: Communications :: Email :: Filters
Project-URL: Homepage, https://github.com/sapristi/mmuxer
Requires-Python: <3.13,>=3.9
Requires-Dist: typer[all]<0.20,>0.19
Requires-Dist: pydantic>2
Requires-Dist: pydantic-settings
Requires-Dist: pyyaml
Requires-Dist: imap-tools==v1.6.0
Requires-Dist: certifi
Requires-Dist: watchfiles>=0.18
Requires-Dist: boolean.py>=4.0
Provides-Extra: systemd
Requires-Dist: cysystemd>=1.6.2; extra == "systemd"
